rene/hints.py
rene/exact.pyi
rene/py.typed
rene/_utils.py
rene/_rene.py
rene/__init__.py
rene/_context.py
rene/_cexact.cpython-39-aarch64-linux-gnu.so
rene/__init__.pyi
rene/_hints.py
rene/exact.py
rene/_crene.cpython-39-aarch64-linux-gnu.so
rene/_exact/polygon.py
rene/_exact/point.py
rene/_exact/contour.py
rene/_exact/box.py
rene/_exact/empty.py
rene/_exact/__init__.py
rene/_exact/trapezoidation.py
rene/_exact/segment.py
rene/_exact/multipolygon.py
rene/_exact/triangulation.py
rene/_exact/multisegment.py
rene/_triangulation/mesh.py
rene/_triangulation/vertices.py
rene/_triangulation/__init__.py
rene/_triangulation/constrained_delaunay.py
rene/_triangulation/quad_edge.py
rene/_triangulation/delaunay.py
rene/_seidel/x_node.py
rene/_seidel/leaf.py
rene/_seidel/__init__.py
rene/_seidel/trapezoidation.py
rene/_seidel/y_node.py
rene/_seidel/edge.py
rene/_seidel/node.py
rene/_seidel/trapezoid.py
rene/_relating/polygon.py
rene/_relating/segment_endpoints.py
rene/_relating/linear.py
rene/_relating/contour.py
rene/_relating/utils.py
rene/_relating/__init__.py
rene/_relating/mixed.py
rene/_relating/sweep_line_key.py
rene/_relating/segment.py
rene/_relating/multipolygon.py
rene/_relating/shaped.py
rene/_relating/event.py
rene/_relating/multisegment.py
rene/_relating/multisegmental.py
rene/_relating/events_queue_key.py
rene/_bentley_ottmann/base.py
rene/_bentley_ottmann/events_registry.py
rene/_bentley_ottmann/__init__.py
rene/_bentley_ottmann/sweep_line_key.py
rene/_bentley_ottmann/event.py
rene/_bentley_ottmann/events_queue_key.py
rene/_clipping/intersection.py
rene/_clipping/linear.py
rene/_clipping/constants.py
rene/_clipping/utils.py
rene/_clipping/difference.py
rene/_clipping/__init__.py
rene/_clipping/union.py
rene/_clipping/mixed.py
rene/_clipping/sweep_line_key.py
rene/_clipping/shaped.py
rene/_clipping/symmetric_difference.py
rene/_clipping/event.py
rene/_clipping/events_queue_key.py
rene-0.1.0.dist-info/LICENSE
rene-0.1.0.dist-info/top_level.txt
rene-0.1.0.dist-info/WHEEL
rene-0.1.0.dist-info/RECORD
rene-0.1.0.dist-info/METADATA
