Metadata-Version: 2.1
Name: rene
Version: 0.1.0
Home-page: https://github.com/lycantropos/rene/
Download-URL: https://github.com/lycantropos/rene/archive/master.zip
Author-email: Azat Ibrakov <azatibrakov@gmail.com>
License: MIT License
Classifier: License :: OSI Approved :: MIT License
Classifier: Programming Language :: Python :: 3.8
Classifier: Programming Language :: Python :: 3.9
Classifier: Programming Language :: Python :: 3.10
Classifier: Programming Language :: Python :: 3.11
Classifier: Programming Language :: Python :: Implementation :: CPython
Classifier: Programming Language :: Python :: Implementation :: PyPy
Requires-Python: >=3.8
License-File: LICENSE
Requires-Dist: dendroid <2.0,>=1.6.1
Requires-Dist: prioq <1.0,>=0.6.0
Requires-Dist: rithm <15.0,>=14.0.0
Requires-Dist: typing-extensions <5.0,>=4.5.0
Provides-Extra: tests
Requires-Dist: hypothesis <7.0,>=6.75.3 ; extra == 'tests'
Requires-Dist: hypothesis-geometry <9.0,>=8.0.0 ; extra == 'tests'
Requires-Dist: pytest <8.0,>=7.3.1 ; extra == 'tests'
